{
  "target": "cobblemon:onix",
  "forms": [
    {
      "name": "Crystal",
      "primaryType": "steel",
	  "pokedex": [
        "cobblemon.species.onix-crystal.desc"
      ],
      "aspects": [
		"crystal"
	  ],
	  "labels": [
		"gen1",
		"legendary"
	  ],
	  "abilities": [
		"waterabsorb",
		"mirrorarmor"
	  ],
		"baseStats": {
		  "hp": 55,
		  "attack": 55,
		  "defence": 160,
		  "special_attack": 30,
		  "special_defence": 65,
		  "speed": 70
		},
		"moves": [
	  	"1:mudsport",
	  	"1:tackle",
	  	"1:harden",
	  	"1:bind",
	  	"1:rockthrow",
	  	"1:rage",
	  	"4:smackdown",
	  	"8:rockpolish",
	  	"12:dragonbreath",
	  	"16:curse",
	  	"20:rockslide",
	  	"24:screech",
	  	"28:sandtomb",
	  	"32:stealthrock",
	  	"36:slam",
	  	"40:sandstorm",
	  	"44:dig",
	  	"48:irontail",
	  	"52:stoneedge",
	  	"56:doubleedge",
	  	"60:powergem",
	  	"egg:block",
	  	"egg:defensecurl",
	  	"egg:dragontail",
	  	"egg:flail",
	  	"egg:headsmash",
	  	"egg:rollout",
	  	"egg:rototiller",
	  	"egg:wideguard",
	  	"tm:ancientpower",
	  	"tm:bind",
	  	"tm:block",
	  	"tm:bodypress",
	  	"tm:bodyslam",
	  	"tm:breakingswipe",
	  	"tm:brutalswing",
	  	"tm:bulldoze",
	  	"tm:curse",
	  	"tm:dig",
	  	"tm:doubleedge",
	  	"tm:dragondance",
	  	"tm:dragonpulse",
	  	"tm:dragontail",
	  	"tm:drillrun",
	  	"tm:earthpower",
	  	"tm:earthquake",
	  	"tm:endure",
	  	"tm:explosion",
	  	"tm:facade",
	  	"tm:flashcannon",
	  	"tm:gyroball",
	  	"tm:headbutt",
	  	"tm:heavyslam",
	  	"tm:highhorsepower",
	  	"tm:ironhead",
	  	"tm:irontail",
	  	"tm:meteorbeam",
	  	"tm:mudslap",
	  	"tm:naturepower",
	  	"tm:payback",
	  	"tm:powershift",
	  	"tm:protect",
	  	"tm:psychup",
	  	"tm:rest",
	  	"tm:roar",
	  	"tm:rockblast",
	  	"tm:rockclimb",
	  	"tm:rockpolish",
	  	"tm:rockslide",
	  	"tm:rocksmash",
	  	"tm:rocktomb",
	  	"tm:rollout",
	  	"tm:sandstorm",
	  	"tm:sandtomb",
	  	"tm:scaryface",
	  	"tm:scorchingsands",
	  	"tm:screech",
	  	"tm:selfdestruct",
	  	"tm:sleeptalk",
	  	"tm:smackdown",
	  	"tm:stealthrock",
	  	"tm:stompingtantrum",
	  	"tm:stoneedge",
	  	"tm:strength",
	  	"tm:substitute",
	  	"tm:sunnyday",
	  	"tm:taunt",
	  	"tm:terablast",
	  	"tm:torment",
	  	"tm:twister",
	  	"tutor:ancientpower",
	  	"tutor:bind",
	  	"tutor:block",
	  	"tutor:bulldoze",
	  	"tutor:dragonpulse",
	  	"tutor:drillrun",
	  	"tutor:earthpower",
	  	"tutor:flashcannon",
	  	"tutor:highhorsepower",
	  	"tutor:ironhead",
	  	"tutor:irontail",
	  	"tutor:meteorbeam",
	  	"tutor:mudslap",
	  	"tutor:powershift",
	  	"tutor:rest",
	  	"tutor:rockslide",
	  	"tutor:rocksmash",
	  	"tutor:rollout",
	  	"tutor:scorchingsands",
	  	"tutor:sleeptalk",
	  	"tutor:stealthrock",
	  	"tutor:stompingtantrum",
	  	"tutor:stoneedge",
	  	"tutor:twister",
	  	"legacy:attract",
	  	"legacy:bide",
	  	"legacy:captivate",
	  	"legacy:confide",
	  	"legacy:doubleteam",
	  	"legacy:fissure",
	  	"legacy:frustration",
	  	"legacy:hiddenpower",
	  	"legacy:mimic",
	  	"legacy:naturalgift",
	  	"legacy:return",
	  	"legacy:round",
	  	"legacy:secretpower",
	  	"legacy:skullbash",
	  	"legacy:snore",
	  	"legacy:swagger",
	  	"legacy:takedown",
	  	"legacy:toxic"
	  ],
	  "evolutions": [
        {
		  "id": "onixcrystal_steelixcrystal",
	  	  "variant": "trade",
		  "result": "steelix crystal=true",
		  "consumeHeldItem": true,
		  "learnableMoves": [],
		  "requirements": [
		    {
			  "variant": "held_item",
			  "itemCondition": "cobblemon:metal_coat"
		    }
		  ]
	    }
	  ]
	}
  ]
}